nand/rtl/nand.v
module nand1(out, in1, in2);
    input in1, in2;
    output out;

    assign out=~(in1&in2);
endmodule

nand/rtl/nand_tb.v
`timescale 1ns/1ns
module nand_tb();
    wire out1;
    reg a, b;

    nand1 n1(out1, a, b);
    //매 1ns마다 a값 반전
    always begin
        #1 a=~a;
    end
    //매 2ns마다 b값 반전
    always begin
        #2 b=~b;
    end
    //초기값설정
    initial begin
        a=0;
        b=0;
        #8 $finish; //8ns에 종료
    end

    initial begin
        $display("Hello World!");
    end

    initial begin
        $dumpfile("output.vcd");
	    $dumpvars(0);
    end
endmodule

nand/output.vcd
$date
	Thu Mar 10 23:22:14 2022
$end
$version
	Icarus Verilog
$end
$timescale
	1ns
$end
$scope module nand_tb $end
$var wire 1 ! out1 $end
$var reg 1 " a $end
$var reg 1 # b $end
$scope module n1 $end
$var wire 1 " in1 $end
$var wire 1 # in2 $end
$var wire 1 ! out $end
$upscope $end
$upscope $end
$enddefinitions $end
#0
$dumpvars
0#
0"
1!
$end
#1
1"
#2
0"
1#
#3
0!
1"
#4
1!
0"
0#
#5
1"
#6
0"
1#
#7
0!
1"
#8
1!
0"
0#
