final_exam_ex/test.v
`timescale 1ns/1ns

module xorgate (out1, in1, in2);
input in1, in2;
output out1;
assign out1 = in1 ^ in2;
specify
(in1,in2 *>out)=3;
endspecify
endmodule
module andgate (out1, in1, in2);
input in1, in2;
output out1;
assign out1 = in1 & in2;
specify
(in1 *> out1) = 3;
(in2 *> out1) = 3;
endspecify
endmodule
module orgate (out1, in1, in2);
input in1, in2;
output out1;
assign out1 = in1 | in2;
specify
(in1 *> out1) = 1;
(in2 *> out1) = 1;
endspecify
endmodule

module notgate(out1,in1);
    input in1;
    output out1;


    specify
        (in1 *> out1)=4;
    endspecify

    assign out1=(~in1);

endmodule



module testb();

 reg a, b, c, d;
 wire x, y, z;
 
 xorgate u1 (z, x, y);
 andgate u2 (x, a, b);
 orgate u3 (y, c, d);


 initial begin
 a=0; b=0; c=0; d=0;
 #20 $finish;
 end

 always
 #4 a = ~a;
 always
 #5 b = ~b;
 always
 #6 c = ~c;
 always
 #7 d = ~d;

 initial begin
    $dumpfile("output.vcd");
    $dumpvars(0);
end

endmodule

final_exam_ex/output.vcd
$date
	Mon Jun 06 16:41:18 2022
$end
$version
	Icarus Verilog
$end
$timescale
	1ns
$end
$scope module notgate $end
$var wire 1 ! in1 $end
$var wire 1 " out1 $end
$upscope $end
$scope module testb $end
$var wire 1 # z $end
$var wire 1 $ y $end
$var wire 1 % x $end
$var reg 1 & a $end
$var reg 1 ' b $end
$var reg 1 ( c $end
$var reg 1 ) d $end
$scope module u1 $end
$var wire 1 # out1 $end
$var wire 1 $ in2 $end
$var wire 1 % in1 $end
$upscope $end
$scope module u2 $end
$var wire 1 & in1 $end
$var wire 1 ' in2 $end
$var wire 1 % out1 $end
$upscope $end
$scope module u3 $end
$var wire 1 ( in1 $end
$var wire 1 ) in2 $end
$var wire 1 $ out1 $end
$upscope $end
$upscope $end
$enddefinitions $end
#0
$dumpvars
0)
0(
0'
0&
0%
0$
0#
z"
z!
$end
#4
1&
#5
1#
1%
1'
#6
0#
1$
1(
#7
1)
#8
1#
0%
0&
#10
0'
#12
1&
0(
#14
0#
0$
0)
#15
1#
1%
1'
#16
0#
0%
0&
#18
1#
1$
1(
#20
1&
0'
