4bit_adder/add4.v
module add_4(a,b,s,cout);
    input [3:0] a,b;
    output [3:0]s;
    output cout;
    
    assign {cout,s}=a+b;
endmodule

4bit_adder/add4_tb.v
`timescale 1ns/1ns
module add4_tb();
  reg [3:0]a,b;
  wire [3:0]s_0451;
  wire cout;

  add_4 test(a,b,s_0451,cout);
  
  initial begin
      a=$urandom%16;
      b=$urandom%16;
      #16 $finish;
  end

  always begin
    #1
      a=$urandom%16;
      b=$urandom%16;
  end

  initial begin
    $dumpfile("output.vcd");
	$dumpvars(0);
  end
endmodule

4bit_adder/output.vcd
$date
	Thu Mar 24 17:29:50 2022
$end
$version
	Icarus Verilog
$end
$timescale
	1ns
$end
$scope module add4_tb $end
$var wire 4 ! s_0451 [3:0] $end
$var wire 1 " cout $end
$var reg 4 # a [3:0] $end
$var reg 4 $ b [3:0] $end
$scope module test $end
$var wire 4 % a [3:0] $end
$var wire 4 & b [3:0] $end
$var wire 4 ' s [3:0] $end
$var wire 1 " cout $end
$upscope $end
$upscope $end
$enddefinitions $end
#0
$dumpvars
b101 '
b1 &
b100 %
b1 $
b100 #
0"
b101 !
$end
#1
b1100 !
b1100 '
b11 $
b11 &
b1001 #
b1001 %
#2
b1010 !
b1010 '
1"
b1101 $
b1101 &
b1101 #
b1101 %
#3
0"
b111 !
b111 '
b10 $
b10 &
b101 #
b101 %
#4
b1110 !
b1110 '
b1101 $
b1101 &
b1 #
b1 %
#5
b11 !
b11 '
1"
b110 #
b110 %
#6
b1001 !
b1001 '
b1100 $
b1100 &
b1101 #
b1101 %
#7
0"
b1111 !
b1111 '
b110 $
b110 &
b1001 #
b1001 %
#8
b1010 $
b1010 &
b101 #
b101 %
#9
b1100 !
b1100 '
b111 $
b111 &
#10
1"
b1 !
b1 '
b1111 $
b1111 &
b10 #
b10 %
#11
b0 !
b0 '
b1110 $
b1110 &
#12
0"
b1101 !
b1101 '
b101 $
b101 &
b1000 #
b1000 %
#13
b1001 !
b1001 '
1"
b1101 $
b1101 &
b1100 #
b1100 %
#14
b10 !
b10 '
b101 $
b101 &
b1101 #
b1101 %
#15
b1101 !
b1101 '
0"
b1010 $
b1010 &
b11 #
b11 %
