testfiles/tb.v
`timescale 1ns/1ns
module test_bench ();
    reg [4:0] in1,in2;
    reg [5:0]out0451;

    initial begin
        //0
        in1=5'b1101;
        in2=5'bx1100;
        out0451=5'bx10;
        //1
        #1
        in1=5'bx;
        in2=-2;
        out0451 = in1 && in2;
        //2
        #1
        out0451 = in1||in2;
        //3
        #1
        out0451 = in1&in2;
        //4
        #1
        out0451 = in1|in2;
        //5
        #1
        in1=-10;
        in2=-2;
        out0451 = in1 && in2;
        //6
        #1
        out0451 = in1||in2;
        //7
        #1
        out0451 = in1&in2;
        //8
        #1
        out0451 = in1|in2;
        //9
        #1
        in1=5'b100z;
        in2=5'b1100;
        out0451=(in1<in2);
        //10
        #1
        in1=5'b1xxz;
        in2=5'b1xxx;
        out0451= (in1===in2);
        //11
        #1
        out0451= (in1==in2);
        //12
        #1
        in1=5'b1001x;
        out0451=&in1;
        //13
        #1
        in1=5'b1001x;
        out0451=^in1;
        //14
        #1
        in1=5'b10011;
        out0451=in1;
        out0451[5]=1;
        //15
        #1
        in1=5'b10011;
        in2=0;
        out0451={1'b1,in1};
        //16
        #1 $finish;
    end

    initial begin
        $dumpfile("output.vcd");
        $dumpvars(0);
    end
    
endmodule

testfiles/output.vcd
$date
	Tue Apr 12 08:17:06 2022
$end
$version
	Icarus Verilog
$end
$timescale
	1ns
$end
$scope module test_bench $end
$var reg 5 ! in1 [4:0] $end
$var reg 5 " in2 [4:0] $end
$var reg 6 # out0451 [5:0] $end
$upscope $end
$enddefinitions $end
#0
$dumpvars
b0xxx10 #
bx1100 "
b1101 !
$end
#1
b0x #
b11110 "
bx !
#2
b1 #
#3
b0xxxx0 #
#4
b1111x #
#5
b1 #
b10110 !
#7
b10110 #
#8
b11110 #
#9
b0x #
b1100 "
b100z !
#10
b0 #
b1xxx "
b1xxz !
#11
b0x #
#12
b0 #
b1001x !
#13
b0x #
#14
b110011 #
b10011 !
#15
b0 "
