proj2/q1/proj2.v
module b7_to_ascii (
    rst,clk,in,r_out,on,out
);
    output reg [6:0]r_out;
    output reg on;
    input rst,clk,in;
    reg [2:0]count;
    output reg [6:0]out;

    always @(negedge rst, posedge clk) begin
        if (rst==0) begin
            out=0;
            r_out=0;
            on=0;
            count=0;
        end
        else begin
            if (count <= 6) begin
                if (count==0) begin
                    on=0;
                end
            out=out<<1;
            out[0]=in;
                if (count==6) begin
                on=1;
                end
            count=count+1;

            if (count==7) begin
                r_out=out;
                count=0;
            end
            end
        end
    end
endmodule

proj2/q1/proj2_tb.v
`timescale 1ns/100ps

module proj2_tb();
    parameter test1_size = 84;
    reg clk,in,reset;
    reg [test1_size-1:0]stream;
    wire on;
    wire [6:0] out_0451;
    reg [7:0] count;
    integer i;

    //bit7_to_ascii tst(reset,clk,stream[i],out);
    b7_to_ascii tst(reset,clk,stream[i],out_0451,on,);

    initial begin
        stream=84'b100100011001011101100110110011011111011111101011111011111110010110110011001000101011;
        reset=0;
        clk=0;
    end

    always #0.5 clk=~clk;

    always @(posedge on) begin
        $display("%c",out_0451);
    end

    initial begin
        #4
        reset=1;

        for (i=test1_size-1;i>=0;i=i-1) begin
            #1;
        end
        #1
        $finish;
    end

    initial begin
        $dumpfile("output.vcd");
        $dumpvars(0);
        
    end
endmodule

proj2/q1/output.vcd
$date
	Thu May 26 19:10:26 2022
$end
$version
	Icarus Verilog
$end
$timescale
	100ps
$end
$scope module proj2_tb $end
$var wire 7 ! out_0451 [6:0] $end
$var wire 1 " on $end
$var reg 1 # clk $end
$var reg 1 $ reset $end
$var reg 84 % stream [83:0] $end
$var integer 32 & i [31:0] $end
$scope module tst $end
$var wire 1 # clk $end
$var wire 1 ' in $end
$var wire 1 $ rst $end
$var reg 3 ( count [2:0] $end
$var reg 1 " on $end
$var reg 7 ) out [6:0] $end
$var reg 7 * r_out [6:0] $end
$upscope $end
$upscope $end
$enddefinitions $end
#0
$dumpvars
b0 *
b0 )
b0 (
x'
bx &
b100100011001011101100110110011011111011111101011111011111110010110110011001000101011 %
0$
0#
0"
b0 !
$end
#5
1#
#10
0#
#15
1#
#20
0#
#25
1#
#30
0#
#35
1#
#40
0#
1'
b1010011 &
1$
#45
b1 (
b1 )
1#
#50
0#
0'
b1010010 &
#55
b10 (
b10 )
1#
#60
0#
b1010001 &
#65
b11 (
b100 )
1#
#70
0#
1'
b1010000 &
#75
b100 (
b1001 )
1#
#80
0#
0'
b1001111 &
#85
b101 (
b10010 )
1#
#90
0#
b1001110 &
#95
b110 (
b100100 )
1#
#100
0#
b1001101 &
#105
b1001000 !
b1001000 *
b0 (
1"
b1001000 )
1#
#110
0#
1'
b1001100 &
#115
b1 (
b10001 )
0"
1#
#120
0#
b1001011 &
#125
b10 (
b100011 )
1#
#130
0#
0'
b1001010 &
#135
b11 (
b1000110 )
1#
#140
0#
b1001001 &
#145
b100 (
b1100 )
1#
#150
0#
1'
b1001000 &
#155
b101 (
b11001 )
1#
#160
0#
0'
b1000111 &
#165
b110 (
b110010 )
1#
#170
0#
1'
b1000110 &
#175
b1100101 !
b1100101 *
b0 (
1"
b1100101 )
1#
#180
0#
b1000101 &
#185
b1 (
b1001011 )
0"
1#
#190
0#
b1000100 &
#195
b10 (
b10111 )
1#
#200
0#
0'
b1000011 &
#205
b11 (
b101110 )
1#
#210
0#
1'
b1000010 &
#215
b100 (
b1011101 )
1#
#220
0#
b1000001 &
#225
b101 (
b111011 )
1#
#230
0#
0'
b1000000 &
#235
b110 (
b1110110 )
1#
#240
0#
b111111 &
#245
b1101100 !
b1101100 *
b0 (
1"
b1101100 )
1#
#250
0#
1'
b111110 &
#255
b1 (
b1011001 )
0"
1#
#260
0#
b111101 &
#265
b10 (
b110011 )
1#
#270
0#
0'
b111100 &
#275
b11 (
b1100110 )
1#
#280
0#
1'
b111011 &
#285
b100 (
b1001101 )
1#
#290
0#
b111010 &
#295
b101 (
b11011 )
1#
#300
0#
0'
b111001 &
#305
b110 (
b110110 )
1#
#310
0#
b111000 &
#315
b0 (
1"
b1101100 )
1#
#320
0#
1'
b110111 &
#325
b1 (
b1011001 )
0"
1#
#330
0#
b110110 &
#335
b10 (
b110011 )
1#
#340
0#
0'
b110101 &
#345
b11 (
b1100110 )
1#
#350
0#
1'
b110100 &
#355
b100 (
b1001101 )
1#
#360
0#
b110011 &
#365
b101 (
b11011 )
1#
#370
0#
b110010 &
#375
b110 (
b110111 )
1#
#380
0#
b110001 &
#385
b1101111 !
b1101111 *
b0 (
1"
b1101111 )
1#
#390
0#
b110000 &
#395
b1 (
b1011111 )
0"
1#
#400
0#
0'
b101111 &
#405
b10 (
b111110 )
1#
#410
0#
1'
b101110 &
#415
b11 (
b1111101 )
1#
#420
0#
b101101 &
#425
b100 (
b1111011 )
1#
#430
0#
b101100 &
#435
b101 (
b1110111 )
1#
#440
0#
b101011 &
#445
b110 (
b1101111 )
1#
#450
0#
b101010 &
#455
b1011111 !
b1011111 *
b0 (
1"
b1011111 )
1#
#460
0#
b101001 &
#465
b1 (
b111111 )
0"
1#
#470
0#
0'
b101000 &
#475
b10 (
b1111110 )
1#
#480
0#
1'
b100111 &
#485
b11 (
b1111101 )
1#
#490
0#
0'
b100110 &
#495
b100 (
b1111010 )
1#
#500
0#
1'
b100101 &
#505
b101 (
b1110101 )
1#
#510
0#
b100100 &
#515
b110 (
b1101011 )
1#
#520
0#
b100011 &
#525
b1010111 !
b1010111 *
b0 (
1"
b1010111 )
1#
#530
0#
b100010 &
#535
b1 (
b101111 )
0"
1#
#540
0#
b100001 &
#545
b10 (
b1011111 )
1#
#550
0#
0'
b100000 &
#555
b11 (
b111110 )
1#
#560
0#
1'
b11111 &
#565
b100 (
b1111101 )
1#
#570
0#
b11110 &
#575
b101 (
b1111011 )
1#
#580
0#
b11101 &
#585
b110 (
b1110111 )
1#
#590
0#
b11100 &
#595
b1101111 !
b1101111 *
b0 (
1"
b1101111 )
1#
#600
0#
b11011 &
#605
b1 (
b1011111 )
0"
1#
#610
0#
b11010 &
#615
b10 (
b111111 )
1#
#620
0#
b11001 &
#625
b11 (
b1111111 )
1#
#630
0#
0'
b11000 &
#635
b100 (
b1111110 )
1#
#640
0#
b10111 &
#645
b101 (
b1111100 )
1#
#650
0#
1'
b10110 &
#655
b110 (
b1111001 )
1#
#660
0#
0'
b10101 &
#665
b1110010 !
b1110010 *
b0 (
1"
b1110010 )
1#
#670
0#
1'
b10100 &
#675
b1 (
b1100101 )
0"
1#
#680
0#
b10011 &
#685
b10 (
b1001011 )
1#
#690
0#
0'
b10010 &
#695
b11 (
b10110 )
1#
#700
0#
1'
b10001 &
#705
b100 (
b101101 )
1#
#710
0#
b10000 &
#715
b101 (
b1011011 )
1#
#720
0#
0'
b1111 &
#725
b110 (
b110110 )
1#
#730
0#
b1110 &
#735
b1101100 !
b1101100 *
b0 (
1"
b1101100 )
1#
#740
0#
1'
b1101 &
#745
b1 (
b1011001 )
0"
1#
#750
0#
b1100 &
#755
b10 (
b110011 )
1#
#760
0#
0'
b1011 &
#765
b11 (
b1100110 )
1#
#770
0#
b1010 &
#775
b100 (
b1001100 )
1#
#780
0#
1'
b1001 &
#785
b101 (
b11001 )
1#
#790
0#
0'
b1000 &
#795
b110 (
b110010 )
1#
#800
0#
b111 &
#805
b1100100 !
b1100100 *
b0 (
1"
b1100100 )
1#
#810
0#
b110 &
#815
b1 (
b1001000 )
0"
1#
#820
0#
1'
b101 &
#825
b10 (
b10001 )
1#
#830
0#
0'
b100 &
#835
b11 (
b100010 )
1#
#840
0#
1'
b11 &
#845
b100 (
b1000101 )
1#
#850
0#
0'
b10 &
#855
b101 (
b1010 )
1#
#860
0#
1'
b1 &
#865
b110 (
b10101 )
1#
#870
0#
b0 &
#875
b101011 !
b101011 *
b0 (
1"
b101011 )
1#
#880
0#
x'
b11111111111111111111111111111111 &
#885
b1 (
b101011x )
0"
1#
