delay_inv/notif1.v
`timescale 10ns/10ns
module not1(
    in,out,cltr
);
    input in,cltr;
    output out;

    notif1 #(4,6,8)(out,in,cltr);
    //rise시간 : 0,x,z 에서 1로 바뀌는데 걸리는시간
    //fall시간 : 1,x,z 에서 0으로 바뀌는데 걸리는시간
    //turn-off : 0,1  ->  z로 바꾸는데 걸리는 시간
    // gate #(delay) : rise,fall 시간이 delay값과 같음
    // gate #(rise,fall) : rise 시간과 fall 시간결정, turn_off는 둘중 작은값
    // gate #(rise,fall,turn-off)

    // (최소시간:전형적인시간:최대시간) 으로 랜덤하게 적용가능, ex: not #(1:2:4, 3:6:10)
    
endmodule

delay_inv/notif1_tb.v
//https://blog.naver.com/beahey/90166877125
`timescale 10ns/10ns
module notif1_tb();
    reg inp;
    reg ctrl1;
    wire out_0451;

    not1 a(inp,out_0451,ctrl1);
// 
    initial begin
        #40 $finish;
    end
    initial begin

        inp=0;
        ctrl1=1;
        #1 inp=1;
        #1 inp=0;
        #1 inp=1;
        #6 inp=0;
        #10 ctrl1=0;
        #8 ctrl1=1;
    end

    initial begin
        $dumpfile("output.vcd");
        $dumpvars(0);
    end
endmodule

delay_inv/output.vcd
$date
	Sat Apr 02 00:58:26 2022
$end
$version
	Icarus Verilog
$end
$timescale
	10ns
$end
$scope module notif1_tb $end
$var wire 1 ! out_0451 $end
$var reg 1 " ctrl1 $end
$var reg 1 # inp $end
$scope module a $end
$var wire 1 " cltr $end
$var wire 1 # in $end
$var wire 1 ! out $end
$upscope $end
$upscope $end
$enddefinitions $end
#0
$dumpvars
0#
1"
x!
$end
#1
1#
#2
0#
#3
1#
#9
0#
0!
#13
1!
#19
0"
#27
1"
z!
#31
1!
